ninette/__init__.py
ninette/alert.py
ninette/cli.py
ninette/config.py
ninette/configuration.py
ninette/constants.py
ninette/database.py
ninette/main.py
ninette/module.py
ninette/options.py
ninette/alerter/__init__.py
ninette/alerter/base.py
ninette/alerter/command.py
ninette/alerter/mail.py
ninette/provider/__init__.py
ninette/provider/base.py
ninette/provider/nina.py
ninette/provider/ping.py
ninette/provider/tagesschau.py
ninette-1.1.0.dist-info/LICENSE
ninette-1.1.0.dist-info/METADATA
ninette-1.1.0.dist-info/WHEEL
ninette-1.1.0.dist-info/entry_points.txt
ninette-1.1.0.dist-info/top_level.txt
ninette-1.1.0.dist-info/RECORD
