Metadata-Version: 2.1
Name: ninette
Version: 1.1.0
Summary: A simple alerting system to get notified about important events or breaking news.
Author-email: Enrico Tröger <enrico.troeger@uvena.de>
License: MIT
Project-URL: Homepage, https://github.com/eht16/ninette
Project-URL: Bug Tracker, https://github.com/eht16/ninette/issues
Keywords: mowas,dwd,nina,warning,alerting
Classifier: Environment :: No Input/Output (Daemon)
Classifier: Development Status :: 5 - Production/Stable
Classifier: Intended Audience :: End Users/Desktop
Classifier: License :: OSI Approved :: MIT License
Classifier: Operating System :: OS Independent
Classifier: Programming Language :: Python
Classifier: Programming Language :: Python :: 3
Classifier: Topic :: Communications
Requires-Python: >=3.8
License-File: LICENSE
Requires-Dist: html2text
Requires-Dist: py-staticmaps
Requires-Dist: requests
